MANIFEST.in
niprov.cfg
setup.cfg
setup.py
acceptance/__init__.py
acceptance/test_api.py
acceptance/test_contextAPI.py
acceptance/test_mongo_backend.py
acceptance/test_terminal.py
executables/provenance
niprov/__init__.py
niprov/adding.py
niprov/approval.py
niprov/basefile.py
niprov/camera.py
niprov/capturing.py
niprov/clock.py
niprov/cnt.py
niprov/commandline.py
niprov/comparing.py
niprov/config.py
niprov/context.py
niprov/dcm.py
niprov/dependencies.py
niprov/diff.py
niprov/discovery.py
niprov/exceptions.py
niprov/exporting.py
niprov/externals.py
niprov/fif.py
niprov/filefilter.py
niprov/files.py
niprov/filesystem.py
niprov/format.py
niprov/formatdict.py
niprov/formatfactory.py
niprov/formatjson.py
niprov/formatnarrated.py
niprov/formatobject.py
niprov/formatsimple.py
niprov/formatxml.py
niprov/hashing.py
niprov/importing.py
niprov/inheriting.py
niprov/inspection.py
niprov/jsonfile.py
niprov/libraries.py
niprov/location.py
niprov/locationfactory.py
niprov/logging.py
niprov/mediumdirect.py
niprov/mediumfactory.py
niprov/mediumfile.py
niprov/mediumstdout.py
niprov/mediumviewer.py
niprov/mnefunsupport.py
niprov/mongo.py
niprov/nifti.py
niprov/parrec.py
niprov/pictures.py
niprov/pipeline.py
niprov/pipelinefactory.py
niprov/querying.py
niprov/recording.py
niprov/renaming.py
niprov/repository.py
niprov/searching.py
niprov/users.py
niprov/views.py
niprov/webapp.py
niprov/xmllib.py
niprov.egg-info/PKG-INFO
niprov.egg-info/SOURCES.txt
niprov.egg-info/dependency_links.txt
niprov.egg-info/entry_points.txt
niprov.egg-info/not-zip-safe
niprov.egg-info/requires.txt
niprov.egg-info/top_level.txt
niprov/static/d3.min.js
niprov/static/jquery-2.1.4.min.js
niprov/static/master.css
niprov/static/moment.min.js
niprov/static/niprov.ico
niprov/static/niprov.js
niprov/static/niprov.png
niprov/static/pipeline.css
niprov/static/pipeline.js
niprov/static/pyramid-16x16.png
niprov/static/svg-crowbar.js
niprov/templates/category.mako
niprov/templates/home.mako
niprov/templates/list.mako
niprov/templates/master.mako
niprov/templates/pipeline.mako
niprov/templates/single.mako
niprov/templates/stats.mako
tests/__init__.py
tests/ditest.py
tests/test_Configuration.py
tests/test_MongoRepo.py
