Metadata-Version: 1.1
Name: niprov
Version: 0.5
Summary: provenance for neuroimaging data
Home-page: https://github.com/ilogue/niprov
Author: Jasper J.F. van den Bosch
Author-email: japsai@gmail.com
License: BSD
Platform: UNKNOWN
Classifier: License :: OSI Approved :: BSD License
Classifier: Intended Audience :: Science/Research
Classifier: Topic :: Scientific/Engineering
